jenkins/__init__.py
jenkins/backup.py
jenkins/restore.py
main/__init__.py
main/jenkins_backup_restore.py
jenkins_backup_restore_cli-1.0.0.dist-info/LICENSE.txt
jenkins_backup_restore_cli-1.0.0.dist-info/METADATA
jenkins_backup_restore_cli-1.0.0.dist-info/WHEEL
jenkins_backup_restore_cli-1.0.0.dist-info/entry_points.txt
jenkins_backup_restore_cli-1.0.0.dist-info/top_level.txt
jenkins_backup_restore_cli-1.0.0.dist-info/RECORD
