Metadata-Version: 2.1
Name: jenkins-backup-restore-cli
Version: 1.0.0
Summary: A Jenkins backup and restore python cli tool with arguments.
Home-page: https://github.com/venkatalolla/jenkins-backup-restore.git
Author: Surya Lolla
Author-email: suryasaicharan93@gmail.com
License: MIT
Keywords: Jenkins backup and restore cli
Platform: UNKNOWN
Classifier: Development Status :: 3 - Alpha
Classifier: Intended Audience :: End Users/Desktop
Classifier: Intended Audience :: Developers
Classifier: Intended Audience :: System Administrators
Classifier: Topic :: System :: Systems Administration
Classifier: Topic :: System :: Recovery Tools
Classifier: License :: OSI Approved :: MIT License
Classifier: Programming Language :: Python :: 3
Classifier: Programming Language :: Python :: 3.5
Classifier: Programming Language :: Python :: 3.6
Classifier: Programming Language :: Python :: 3.7
Classifier: Programming Language :: Python :: 3.8
Classifier: Operating System :: MacOS :: MacOS X
Classifier: Operating System :: POSIX
Requires-Dist: pyfiglet
Requires-Dist: botocore
Requires-Dist: boto3
Requires-Dist: argparse
